up2smms.py
up2smms-0.1.0.dist-info/METADATA
up2smms-0.1.0.dist-info/WHEEL
up2smms-0.1.0.dist-info/top_level.txt
up2smms-0.1.0.dist-info/RECORD
