Metadata-Version: 2.1
Name: up2smms
Version: 0.1.0
Summary: Save uploaded pictures in Sm.ms.
Home-page: https://github.com/staugur/picbed-up2smms
Author: staugur
Author-email: staugur@saintic.com
License: BSD 3-Clause
Platform: UNKNOWN
Requires-Dist: requests
